topyary/__init__.py
topyary/events/__init__.py
topyary/events/inotify.py
topyary/events/loop.py
topyary/events/proactor.py
topyary_events-0.1.1.dist-info/METADATA
topyary_events-0.1.1.dist-info/WHEEL
topyary_events-0.1.1.dist-info/top_level.txt
topyary_events-0.1.1.dist-info/RECORD
